microbitdongle/__init__.py
microbitdongle/dongle.py
microbitdongle-0.3.12.dist-info/METADATA
microbitdongle-0.3.12.dist-info/RECORD
microbitdongle-0.3.12.dist-info/WHEEL
microbitdongle-0.3.12.dist-info/top_level.txt
