Metadata-Version: 2.1
Name: microbitdongle
Version: 0.3.12
Summary: UNKNOWN
Home-page: https://github.com/lukespademan/microbitdongle
Author: Luke Spademan
Author-email: info@lukespademan.com
License: UNKNOWN
Download-URL: https://github.com/lukespademan/microbitdongle/archive/0.1.tar.gz
Platform: UNKNOWN
Requires-Dist: pyserial
